slotdata/__init__.py
slotdata/__main__.py
slotdata/core/__init__.py
slotdata/tests/__init__.py
slotdata/tests/test_1984.py
slotdata-0.0.1.dev3.dist-info/LICENSE.txt
slotdata-0.0.1.dev3.dist-info/METADATA
slotdata-0.0.1.dev3.dist-info/WHEEL
slotdata-0.0.1.dev3.dist-info/top_level.txt
slotdata-0.0.1.dev3.dist-info/RECORD
