Metadata-Version: 2.2
Name: slotdata
Version: 0.0.1.dev3
Summary: This project provides implementations of magic methods for __slots__ based classes.
Author-email: Johannes <johannes-programming@mailfence.com>
License: The MIT License (MIT)
Project-URL: Download, https://pypi.org/project/slotdata/#files
Project-URL: Index, https://pypi.org/project/slotdata/
Project-URL: Source, https://github.com/johannes-programming/slotdata/
Project-URL: Website, https://slotdata.johannes-programming.online/
Classifier: Development Status :: 2 - Pre-Alpha
Classifier: License :: OSI Approved :: MIT License
Classifier: Natural Language :: English
Classifier: Operating System :: OS Independent
Classifier: Programming Language :: Python
Classifier: Programming Language :: Python :: 3
Classifier: Programming Language :: Python :: 3 :: Only
Requires-Python: >=3.8
License-File: LICENSE.txt
